datafollowers_mbti-0.3.1.dist-info/METADATA
datafollowers_mbti-0.3.1.dist-info/WHEEL
datafollowers_mbti-0.3.1.dist-info/entry_points.txt
mbti/__init__.py
mbti/cli.py
datafollowers_mbti-0.3.1.dist-info/RECORD
