Metadata-Version: 2.1
Name: DataFollowers-MBTI
Version: 0.3.1
Summary: Default template for PDM package
Author-Email: vhzkclq0705 <vhzkclq0705@naver.com>
License: MIT
Requires-Python: >=3.10
Requires-Dist: typer>=0.15.1
Requires-Dist: pytest>=8.3.4
